tests/__init__.py
tests/test_plot.py
toopy/__init__.py
toopy/benchmarking.py
toopy/casyfile.py
toopy/config.py
toopy/file.py
toopy/nutrient_timers.py
toopy/pandas.py
toopy/param.py
toopy/plot.py
toopy/remote.py
toopy-0.6.0.dist-info/LICENSE
toopy-0.6.0.dist-info/METADATA
toopy-0.6.0.dist-info/WHEEL
toopy-0.6.0.dist-info/entry_points.txt
toopy-0.6.0.dist-info/top_level.txt
toopy-0.6.0.dist-info/RECORD
