Metadata-Version: 2.1
Name: toopy
Version: 0.6.0
Summary: Tools for python
Author-email: Florian Schunck <fluncki@protonmail.com>
License: GNU GENERAL PUBLIC LICENSE
Project-URL: Homepage, https://github.com/flo-schu/toopy
Project-URL: Issue Tracker, https://github.com/flo-schu/toopy/issues
Classifier: Development Status :: 4 - Beta
Classifier: Programming Language :: Python :: 3
Classifier: Natural Language :: English
Classifier: License :: OSI Approved :: GNU General Public License v3 (GPLv3)
Classifier: Operating System :: OS Independent
Requires-Python: >=3.10
License-File: LICENSE
Requires-Dist: pandas >=1.4
Requires-Dist: numpy >=1.23
Requires-Dist: matplotlib >=3.5
Requires-Dist: psutil ~=5.9.5
